{
  "calls": [
    {
      "date": "2026-06-09",
      "symbol": "RELIANCE",
      "exchange": "NS",
      "name": "Reliance Industries",
      "stance": "Watch",
      "confidence": "Low",
      "priceAtCall": 1264.2,
      "indexSymbol": "^NSEI",
      "indexAtCall": 23195.55,
      "reasoning": "Automated analysis was unavailable this run (model or parse error). Recorded as Watch, which is not scored.",
      "keyNews": [],
      "outcome": "unscored",
      "evaluatedPrice": 1270,
      "evaluatedIndexPrice": 23347.85,
      "stockReturnPct": 0.45878816642936915,
      "benchmarkReturnPct": 0.6565914582753907,
      "benchmarked": true,
      "evaluatedDate": "2026-06-10"
    },
    {
      "date": "2026-06-09",
      "symbol": "TCS",
      "exchange": "NS",
      "name": "Tata Consultancy Services",
      "stance": "Watch",
      "confidence": "Low",
      "priceAtCall": 2147.7,
      "indexSymbol": "^NSEI",
      "indexAtCall": 23195.55,
      "reasoning": "Automated analysis was unavailable this run (model or parse error). Recorded as Watch, which is not scored.",
      "keyNews": [],
      "outcome": "unscored",
      "evaluatedPrice": 2159,
      "evaluatedIndexPrice": 23347.85,
      "stockReturnPct": 0.5261442473343703,
      "benchmarkReturnPct": 0.6565914582753907,
      "benchmarked": true,
      "evaluatedDate": "2026-06-10"
    },
    {
      "date": "2026-06-09",
      "symbol": "HDFCBANK",
      "exchange": "NS",
      "name": "HDFC Bank",
      "stance": "Watch",
      "confidence": "Low",
      "priceAtCall": 735,
      "indexSymbol": "^NSEI",
      "indexAtCall": 23195.55,
      "reasoning": "Automated analysis was unavailable this run (model or parse error). Recorded as Watch, which is not scored.",
      "keyNews": [],
      "outcome": "unscored",
      "evaluatedPrice": 743.1,
      "evaluatedIndexPrice": 23347.85,
      "stockReturnPct": 1.1020408163265438,
      "benchmarkReturnPct": 0.6565914582753907,
      "benchmarked": true,
      "evaluatedDate": "2026-06-10"
    },
    {
      "date": "2026-06-10",
      "symbol": "RELIANCE",
      "exchange": "NS",
      "name": "Reliance Industries",
      "stance": "Watch",
      "confidence": "Low",
      "priceAtCall": 1270,
      "indexSymbol": "^NSEI",
      "indexAtCall": 23347.85,
      "reasoning": "Automated analysis was unavailable this run (model or parse error). Recorded as Watch, which is not scored.",
      "keyNews": [],
      "outcome": "unscored",
      "evaluatedPrice": 1266.9,
      "evaluatedIndexPrice": 23232.75,
      "stockReturnPct": -0.24409448818897284,
      "benchmarkReturnPct": -0.4929790109153509,
      "benchmarked": true,
      "evaluatedDate": "2026-06-11"
    },
    {
      "date": "2026-06-10",
      "symbol": "TCS",
      "exchange": "NS",
      "name": "Tata Consultancy Services",
      "stance": "Watch",
      "confidence": "Low",
      "priceAtCall": 2159,
      "indexSymbol": "^NSEI",
      "indexAtCall": 23347.85,
      "reasoning": "Automated analysis was unavailable this run (model or parse error). Recorded as Watch, which is not scored.",
      "keyNews": [],
      "outcome": "unscored",
      "evaluatedPrice": 2133.3,
      "evaluatedIndexPrice": 23232.75,
      "stockReturnPct": -1.190365910143576,
      "benchmarkReturnPct": -0.4929790109153509,
      "benchmarked": true,
      "evaluatedDate": "2026-06-11"
    },
    {
      "date": "2026-06-10",
      "symbol": "HDFCBANK",
      "exchange": "NS",
      "name": "HDFC Bank",
      "stance": "Watch",
      "confidence": "Low",
      "priceAtCall": 743.1,
      "indexSymbol": "^NSEI",
      "indexAtCall": 23347.85,
      "reasoning": "Automated analysis was unavailable this run (model or parse error). Recorded as Watch, which is not scored.",
      "keyNews": [],
      "outcome": "unscored",
      "evaluatedPrice": 749.45,
      "evaluatedIndexPrice": 23232.75,
      "stockReturnPct": 0.854528327277615,
      "benchmarkReturnPct": -0.4929790109153509,
      "benchmarked": true,
      "evaluatedDate": "2026-06-11"
    },
    {
      "date": "2026-06-11",
      "symbol": "RELIANCE",
      "exchange": "NS",
      "name": "Reliance Industries",
      "stance": "Watch",
      "confidence": "Low",
      "priceAtCall": 1266.9,
      "indexSymbol": "^NSEI",
      "indexAtCall": 23232.75,
      "reasoning": "Automated analysis was unavailable this run (model or parse error). Recorded as Watch, which is not scored.",
      "keyNews": [],
      "outcome": "unscored",
      "evaluatedPrice": 1267.8,
      "evaluatedIndexPrice": 23376.65,
      "stockReturnPct": 0.07103954534690704,
      "benchmarkReturnPct": 0.6193842743541067,
      "benchmarked": true,
      "evaluatedDate": "2026-06-12"
    },
    {
      "date": "2026-06-11",
      "symbol": "TCS",
      "exchange": "NS",
      "name": "Tata Consultancy Services",
      "stance": "Watch",
      "confidence": "Low",
      "priceAtCall": 2133.3,
      "indexSymbol": "^NSEI",
      "indexAtCall": 23232.75,
      "reasoning": "Automated analysis was unavailable this run (model or parse error). Recorded as Watch, which is not scored.",
      "keyNews": [],
      "outcome": "unscored",
      "evaluatedPrice": 2152.8,
      "evaluatedIndexPrice": 23376.65,
      "stockReturnPct": 0.9140767824497242,
      "benchmarkReturnPct": 0.6193842743541067,
      "benchmarked": true,
      "evaluatedDate": "2026-06-12"
    },
    {
      "date": "2026-06-11",
      "symbol": "HDFCBANK",
      "exchange": "NS",
      "name": "HDFC Bank",
      "stance": "Watch",
      "confidence": "Low",
      "priceAtCall": 749.45,
      "indexSymbol": "^NSEI",
      "indexAtCall": 23232.75,
      "reasoning": "Automated analysis was unavailable this run (model or parse error). Recorded as Watch, which is not scored.",
      "keyNews": [],
      "outcome": "unscored",
      "evaluatedPrice": 761,
      "evaluatedIndexPrice": 23376.65,
      "stockReturnPct": 1.5411301621188755,
      "benchmarkReturnPct": 0.6193842743541067,
      "benchmarked": true,
      "evaluatedDate": "2026-06-12"
    },
    {
      "date": "2026-06-12",
      "symbol": "RELIANCE",
      "exchange": "NS",
      "name": "Reliance Industries",
      "stance": "Watch",
      "confidence": "Low",
      "priceAtCall": 1267.8,
      "indexSymbol": "^NSEI",
      "indexAtCall": 23376.65,
      "reasoning": "Automated analysis was unavailable this run (model or parse error). Recorded as Watch, which is not scored.",
      "keyNews": [],
      "outcome": "unscored",
      "evaluatedPrice": 1293,
      "evaluatedIndexPrice": 23622.9,
      "stockReturnPct": 1.9876952200662545,
      "benchmarkReturnPct": 1.0534015780704342,
      "benchmarked": true,
      "evaluatedDate": "2026-06-13"
    },
    {
      "date": "2026-06-12",
      "symbol": "TCS",
      "exchange": "NS",
      "name": "Tata Consultancy Services",
      "stance": "Watch",
      "confidence": "Low",
      "priceAtCall": 2152.8,
      "indexSymbol": "^NSEI",
      "indexAtCall": 23376.65,
      "reasoning": "Automated analysis was unavailable this run (model or parse error). Recorded as Watch, which is not scored.",
      "keyNews": [],
      "outcome": "unscored",
      "evaluatedPrice": 2161.4,
      "evaluatedIndexPrice": 23622.9,
      "stockReturnPct": 0.3994797473058309,
      "benchmarkReturnPct": 1.0534015780704342,
      "benchmarked": true,
      "evaluatedDate": "2026-06-13"
    },
    {
      "date": "2026-06-12",
      "symbol": "HDFCBANK",
      "exchange": "NS",
      "name": "HDFC Bank",
      "stance": "Watch",
      "confidence": "Low",
      "priceAtCall": 761,
      "indexSymbol": "^NSEI",
      "indexAtCall": 23376.65,
      "reasoning": "Automated analysis was unavailable this run (model or parse error). Recorded as Watch, which is not scored.",
      "keyNews": [],
      "outcome": "unscored",
      "evaluatedPrice": 772.45,
      "evaluatedIndexPrice": 23622.9,
      "stockReturnPct": 1.5045992115637397,
      "benchmarkReturnPct": 1.0534015780704342,
      "benchmarked": true,
      "evaluatedDate": "2026-06-13"
    },
    {
      "date": "2026-06-13",
      "symbol": "RELIANCE",
      "exchange": "NS",
      "name": "Reliance Industries",
      "stance": "Watch",
      "confidence": "Low",
      "priceAtCall": 1293,
      "indexSymbol": "^NSEI",
      "indexAtCall": 23622.9,
      "reasoning": "Automated analysis was unavailable this run (model or parse error). Recorded as Watch, which is not scored.",
      "keyNews": [],
      "outcome": "unscored",
      "evaluatedPrice": 1293,
      "evaluatedIndexPrice": 23622.9,
      "stockReturnPct": 0,
      "benchmarkReturnPct": 0,
      "benchmarked": true,
      "evaluatedDate": "2026-06-14"
    },
    {
      "date": "2026-06-13",
      "symbol": "TCS",
      "exchange": "NS",
      "name": "Tata Consultancy Services",
      "stance": "Watch",
      "confidence": "Low",
      "priceAtCall": 2161.4,
      "indexSymbol": "^NSEI",
      "indexAtCall": 23622.9,
      "reasoning": "Automated analysis was unavailable this run (model or parse error). Recorded as Watch, which is not scored.",
      "keyNews": [],
      "outcome": "unscored",
      "evaluatedPrice": 2161.4,
      "evaluatedIndexPrice": 23622.9,
      "stockReturnPct": 0,
      "benchmarkReturnPct": 0,
      "benchmarked": true,
      "evaluatedDate": "2026-06-14"
    },
    {
      "date": "2026-06-13",
      "symbol": "HDFCBANK",
      "exchange": "NS",
      "name": "HDFC Bank",
      "stance": "Watch",
      "confidence": "Low",
      "priceAtCall": 772.45,
      "indexSymbol": "^NSEI",
      "indexAtCall": 23622.9,
      "reasoning": "Automated analysis was unavailable this run (model or parse error). Recorded as Watch, which is not scored.",
      "keyNews": [],
      "outcome": "unscored",
      "evaluatedPrice": 772.45,
      "evaluatedIndexPrice": 23622.9,
      "stockReturnPct": 0,
      "benchmarkReturnPct": 0,
      "benchmarked": true,
      "evaluatedDate": "2026-06-14"
    },
    {
      "date": "2026-06-13",
      "symbol": "RELIANCE",
      "exchange": "NS",
      "name": "Reliance Industries",
      "stance": "Watch",
      "confidence": "Low",
      "priceAtCall": 1293,
      "indexSymbol": "^NSEI",
      "indexAtCall": 23622.9,
      "reasoning": "Automated analysis was unavailable this run (model or parse error). Recorded as Watch, which is not scored.",
      "keyNews": [],
      "outcome": "unscored",
      "evaluatedPrice": 1293,
      "evaluatedIndexPrice": 23622.9,
      "stockReturnPct": 0,
      "benchmarkReturnPct": 0,
      "benchmarked": true,
      "evaluatedDate": "2026-06-14"
    },
    {
      "date": "2026-06-13",
      "symbol": "TCS",
      "exchange": "NS",
      "name": "Tata Consultancy Services",
      "stance": "Watch",
      "confidence": "Low",
      "priceAtCall": 2161.4,
      "indexSymbol": "^NSEI",
      "indexAtCall": 23622.9,
      "reasoning": "Automated analysis was unavailable this run (model or parse error). Recorded as Watch, which is not scored.",
      "keyNews": [],
      "outcome": "unscored",
      "evaluatedPrice": 2161.4,
      "evaluatedIndexPrice": 23622.9,
      "stockReturnPct": 0,
      "benchmarkReturnPct": 0,
      "benchmarked": true,
      "evaluatedDate": "2026-06-14"
    },
    {
      "date": "2026-06-13",
      "symbol": "HDFCBANK",
      "exchange": "NS",
      "name": "HDFC Bank",
      "stance": "Watch",
      "confidence": "Low",
      "priceAtCall": 772.45,
      "indexSymbol": "^NSEI",
      "indexAtCall": 23622.9,
      "reasoning": "Automated analysis was unavailable this run (model or parse error). Recorded as Watch, which is not scored.",
      "keyNews": [],
      "outcome": "unscored",
      "evaluatedPrice": 772.45,
      "evaluatedIndexPrice": 23622.9,
      "stockReturnPct": 0,
      "benchmarkReturnPct": 0,
      "benchmarked": true,
      "evaluatedDate": "2026-06-14"
    },
    {
      "date": "2026-06-14",
      "symbol": "RELIANCE",
      "exchange": "NS",
      "name": "Reliance Industries",
      "stance": "Watch",
      "confidence": "Low",
      "priceAtCall": 1293,
      "indexSymbol": "^NSEI",
      "indexAtCall": 23622.9,
      "reasoning": "Automated analysis was unavailable this run (model, credit, or parse error). Recorded as Watch, which is not scored.",
      "keyNews": [],
      "sources": [],
      "outcome": "pending"
    },
    {
      "date": "2026-06-14",
      "symbol": "TCS",
      "exchange": "NS",
      "name": "Tata Consultancy Services",
      "stance": "Watch",
      "confidence": "Low",
      "priceAtCall": 2161.4,
      "indexSymbol": "^NSEI",
      "indexAtCall": 23622.9,
      "reasoning": "Automated analysis was unavailable this run (model, credit, or parse error). Recorded as Watch, which is not scored.",
      "keyNews": [],
      "sources": [],
      "outcome": "pending"
    },
    {
      "date": "2026-06-14",
      "symbol": "HDFCBANK",
      "exchange": "NS",
      "name": "HDFC Bank",
      "stance": "Watch",
      "confidence": "Low",
      "priceAtCall": 772.45,
      "indexSymbol": "^NSEI",
      "indexAtCall": 23622.9,
      "reasoning": "Automated analysis was unavailable this run (model, credit, or parse error). Recorded as Watch, which is not scored.",
      "keyNews": [],
      "sources": [],
      "outcome": "pending"
    }
  ]
}
